logze/__init__.py
logze/models/__init__.py
logze/models/log.py
logze/recorder/__init__.py
logze/recorder/logger.py
logze-0.1.8.dist-info/LICENSE
logze-0.1.8.dist-info/METADATA
logze-0.1.8.dist-info/WHEEL
logze-0.1.8.dist-info/top_level.txt
logze-0.1.8.dist-info/RECORD
