Metadata-Version: 2.1
Name: logze
Version: 0.1.8
Summary: Library in Python to store logs in MongoDB and send notifications of errors to Microsoft Teams
Home-page: https://github.com/josehenriqueroveda/logze
Author: Jose Henrique Roveda
Author-email: josehenriqueroveda@usp.br
Classifier: Development Status :: 4 - Beta
Classifier: Intended Audience :: Developers
Classifier: License :: OSI Approved :: MIT License
Classifier: Programming Language :: Python :: 3
Classifier: Programming Language :: Python :: 3.7
Classifier: Programming Language :: Python :: 3.8
Classifier: Programming Language :: Python :: 3.9
Classifier: Programming Language :: Python :: 3.10
Classifier: Programming Language :: Python :: 3.11
License-File: LICENSE
Requires-Dist: pymongo
Requires-Dist: requests
